{
  "timestamp": "2025-11-14T23:14:05.126837",
  "regime_detection": {
    "regime": 1,
    "regime_name": "Steady Growth",
    "start_date": "2025-10-21",
    "end_date": "2025-11-14",
    "days_in_regime": 24,
    "as_of": "2025-11-14",
    "characteristics": {
      "mean_return": 0.0685396421385283,
      "volatility": 0.1800815639361999,
      "sharpe": 0.38060332573972333
    },
    "all_probabilities": {
      "Strong Bull": 0.2822405557967868,
      "Steady Growth": 0.6547980894485455,
      "Crisis/Bear": 0.06296135475466781
    },
    "confidence": 0.6547980894485455
  },
  "recommended_weights": {
    "momentum": 45.0,
    "quality": 20.0,
    "growth": 10.0,
    "technical": 10.0,
    "credit": 10.0,
    "financial_health": 10.0,
    "value": 5.0,
    "size": -5.0,
    "volatility_penalty": -5.0,
    "carry": 0.0,
    "liquidity": 3.0,
    "insider": -3.0
  },
  "source": "historical_analysis",
  "note": "Current regime based on latest historical regime analysis"
}